telegramTransfer/__init__.py
telegramtransfer-0.1.0.dist-info/METADATA
telegramtransfer-0.1.0.dist-info/WHEEL
telegramtransfer-0.1.0.dist-info/entry_points.txt
telegramtransfer-0.1.0.dist-info/licenses/LICENSE
telegramtransfer-0.1.0.dist-info/RECORD
