Metadata-Version: 2.4
Name: telegramTransfer
Version: 0.1.0
Summary: A tool for transferring files through Telegram
Project-URL: Homepage, https://github.com/ooopus/telegramTransfer
Project-URL: Repository, https://github.com/ooopus/telegramTransfer.git
Author: ooopus
License:                     GNU GENERAL PUBLIC LICENSE
License-File: LICENSE
Classifier: Development Status :: 4 - Beta
Classifier: Environment :: Console
Classifier: Intended Audience :: End Users/Desktop
Classifier: License :: OSI Approved :: GNU General Public License v3 (GPLv3)
Classifier: Operating System :: OS Independent
Classifier: Programming Language :: Python :: 3
Classifier: Programming Language :: Python :: 3.8
Classifier: Programming Language :: Python :: 3.9
Classifier: Programming Language :: Python :: 3.10
Classifier: Programming Language :: Python :: 3.11
Classifier: Topic :: Communications :: File Sharing
Requires-Python: >=3.8
Requires-Dist: click>=8.1.3
Requires-Dist: cryptography>=41.0.3
Requires-Dist: loguru>=0.7.0
Requires-Dist: python-dotenv
Requires-Dist: pyyaml>=6.0.1
Requires-Dist: telethon>=1.28.5
Requires-Dist: tqdm>=4.65.0
